dphon/__init__.py
dphon/align.py
dphon/cli.py
dphon/console.py
dphon/corpus.py
dphon/extend.py
dphon/g2p.py
dphon/index.py
dphon/match.py
dphon/ngrams.py
dphon/reuse.py
dphon/data/oc-consonants.txt
dphon/data/oc-vowels.txt
dphon/data/sound_table_v1.json
dphon/data/sound_table_v2.json
dphon-2.1.0.dist-info/licenses/LICENSE
dphon-2.1.0.dist-info/METADATA
dphon-2.1.0.dist-info/WHEEL
dphon-2.1.0.dist-info/entry_points.txt
dphon-2.1.0.dist-info/top_level.txt
dphon-2.1.0.dist-info/RECORD
