Metadata-Version: 2.4
Name: dphon
Version: 2.1.0
Summary: Tools and algorithms for phonology-aware Early Chinese NLP.
Author-email: Nick Budak <budak@stanford.edu>, Gian Duri Rominger <gromin@uw.edu>
License: MIT License
Project-URL: Repository, https://github.com/direct-phonology/dphon
Project-URL: Issues, https://github.com/direct-phonology/dphon/issues
Project-URL: Documentation, https://direct-phonology.github.io/dphon/
Keywords: old chinese,early chinese,phonology,linguistics,nlp
Classifier: Environment :: Console
Classifier: Intended Audience :: Science/Research
Classifier: License :: OSI Approved :: MIT License
Classifier: Natural Language :: Chinese (Traditional)
Classifier: Operating System :: OS Independent
Classifier: Programming Language :: Python :: 3.8
Classifier: Programming Language :: Python :: 3.9
Classifier: Programming Language :: Python :: 3.10
Classifier: Programming Language :: Python :: 3
Classifier: Programming Language :: Python :: 3 :: Only
Classifier: Topic :: Text Processing :: Linguistic
Classifier: Topic :: Utilities
Requires-Python: >=3.8
License-File: LICENSE
Requires-Dist: docopt
Requires-Dist: spacy>=3
Requires-Dist: Levenshtein
Requires-Dist: lingpy
Requires-Dist: rich
Requires-Dist: jsonlines
Provides-Extra: dev
Requires-Dist: check-manifest; extra == "dev"
Requires-Dist: mypy; extra == "dev"
Requires-Dist: pylint; extra == "dev"
Provides-Extra: test
Requires-Dist: coverage; extra == "test"
Dynamic: license-file
